inkscape_figure_manager/__init__.py
inkscape_figure_manager/__main__.py
inkscape_figure_manager/daemon.py
inkscape_figure_manager/picker.py
inkscape_figure_manager/template.svg
inkscape_figure_manager/watcher.py
inkscape_figure_manager/watcher_daemon.py
inkscape_figure_manager-0.1.0.dist-info/entry_points.txt
inkscape_figure_manager-0.1.0.dist-info/LICENSE
inkscape_figure_manager-0.1.0.dist-info/WHEEL
inkscape_figure_manager-0.1.0.dist-info/METADATA
inkscape_figure_manager-0.1.0.dist-info/RECORD
