Metadata-Version: 2.1
Name: inkscape_figure_manager
Version: 0.1.0
Summary: An API for managing inkscape figures.
Author: Silas Waxter, Gille Castel
Classifier: Programming Language :: Python :: 3
Classifier: Operating System :: POSIX :: Linux
Requires-Dist: click
Requires-Dist: appdirs
Requires-Dist: watchdog
Requires-Dist: psutil
Project-URL: Bug Tracker, https://github.com/silaswaxter/inkscape-figure-manager/issues
Project-URL: Homepage, https://github.com/silaswaxter/inkscape-figure-manager
